eosfactory/__init__.py
eosfactory/build.py
eosfactory/config.py
eosfactory/create_project.py
eosfactory/deploy.py
eosfactory/eosf.py
eosfactory/install.py
eosfactory/pack_contract.py
eosfactory/register_testnet.py
eosfactory/register_testnet_via_faucet.py
eosfactory/save_code.py
eosfactory/testnets.py
eosfactory/core/__init__.py
eosfactory/core/account.py
eosfactory/core/checklist.py
eosfactory/core/cleos.py
eosfactory/core/cleos_get.py
eosfactory/core/cleos_set.py
eosfactory/core/cleos_sys.py
eosfactory/core/config.py
eosfactory/core/const.py
eosfactory/core/errors.py
eosfactory/core/interface.py
eosfactory/core/logger.py
eosfactory/core/manager.py
eosfactory/core/setup.py
eosfactory/core/teos.py
eosfactory/core/testnet.py
eosfactory/core/utils.py
eosfactory/core/vscode.py
eosfactory/shell/__init__.py
eosfactory/shell/account.py
eosfactory/shell/contract.py
eosfactory/shell/wallet.py
eosfactory_tokenika-3.4.0.data/data/eosfactory/wsl_root.sh
eosfactory_tokenika-3.4.0.data/data/eosfactory/config/config.ini
eosfactory_tokenika-3.4.0.data/data/eosfactory/config/config.json
eosfactory_tokenika-3.4.0.data/data/eosfactory/contracts/eosio_token/.eosideignore
eosfactory_tokenika-3.4.0.data/data/eosfactory/contracts/eosio_token/CMakeLists.txt
eosfactory_tokenika-3.4.0.data/data/eosfactory/contracts/eosio_token/.vscode/settings.json
eosfactory_tokenika-3.4.0.data/data/eosfactory/contracts/eosio_token/.vscode/tasks.json
eosfactory_tokenika-3.4.0.data/data/eosfactory/contracts/eosio_token/.vscode/ipch/961205d7e6e61112/mmap_address.bin
eosfactory_tokenika-3.4.0.data/data/eosfactory/contracts/eosio_token/include/eosio_token.hpp
eosfactory_tokenika-3.4.0.data/data/eosfactory/contracts/eosio_token/ricardian/eosio_token.clauses.md
eosfactory_tokenika-3.4.0.data/data/eosfactory/contracts/eosio_token/ricardian/eosio_token.contracts.md
eosfactory_tokenika-3.4.0.data/data/eosfactory/contracts/eosio_token/src/eosio_token.cpp
eosfactory_tokenika-3.4.0.dist-info/DESCRIPTION.rst
eosfactory_tokenika-3.4.0.dist-info/METADATA
eosfactory_tokenika-3.4.0.dist-info/RECORD
eosfactory_tokenika-3.4.0.dist-info/WHEEL
eosfactory_tokenika-3.4.0.dist-info/metadata.json
eosfactory_tokenika-3.4.0.dist-info/top_level.txt
