Metadata-Version: 2.0
Name: eosfactory-tokenika
Version: 3.4.0
Summary: Python-based EOS smart-contract development & testing framework
Home-page: https://github.com/tokenika/eosfactory
Author: Tokenika
Author-email: contact@tokenika.io
License: MIT
Keywords: EOSIO,smart contract unit testing
Platform: UNKNOWN
Classifier: Programming Language :: Python :: 3.5
Classifier: License :: OSI Approved :: MIT License
Classifier: Operating System :: Unix
Classifier: Topic :: Software Development :: Testing
Requires-Dist: psutil
Requires-Dist: termcolor
